ViscaBarca/__init__.py
ViscaBarca/pokemon.csv
ViscaBarca/random_pokemon.py
ViscaBarca-1.0.2.dist-info/METADATA
ViscaBarca-1.0.2.dist-info/WHEEL
ViscaBarca-1.0.2.dist-info/top_level.txt
ViscaBarca-1.0.2.dist-info/RECORD
