Metadata-Version: 2.1
Name: ViscaBarca
Version: 1.0.2
Summary: Libreria para generar un pokemon aleatorio
Author: Angel Flores 
Requires-Dist: pandas
